LICENSE
MANIFEST.in
README.md
pyproject.toml
setup.py
kos_sim/__init__.py
kos_sim/py.typed
kos_sim/requirements.txt
kos_sim/server.py
kos_sim/services.py
kos_sim/simulator.py
kos_sim/video_recorder.py
kos_sim.egg-info/PKG-INFO
kos_sim.egg-info/SOURCES.txt
kos_sim.egg-info/dependency_links.txt
kos_sim.egg-info/requires.txt
kos_sim.egg-info/top_level.txt
scripts/kos-sim
tests/test_dummy.py