Metadata-Version: 2.4
Name: kos-sim
Version: 0.0.14
Summary: The simulator backend for the K-Scale Operating System (KOS)
Home-page: https://github.com/kscalelabs/kos-sim.git
Author: K-Scale Labs <ben@kscale.dev>
Requires-Python: >=3.11
License-File: LICENSE
Requires-Dist: colorlogging
Requires-Dist: kscale
Requires-Dist: mujoco
Requires-Dist: mujoco-scenes
Requires-Dist: kmv
Requires-Dist: numpy
Requires-Dist: omegaconf
Requires-Dist: pykos
Requires-Dist: onnxruntime
Requires-Dist: scipy
Requires-Dist: mediapy
Provides-Extra: dev
Requires-Dist: black; extra == "dev"
Requires-Dist: darglint; extra == "dev"
Requires-Dist: mypy; extra == "dev"
Requires-Dist: pytest; extra == "dev"
Requires-Dist: ruff; extra == "dev"
Provides-Extra: examples
Requires-Dist: scipy; extra == "examples"
Requires-Dist: kinfer; extra == "examples"
Dynamic: author
Dynamic: description
Dynamic: description-content-type
Dynamic: home-page
Dynamic: license-file
Dynamic: provides-extra
Dynamic: requires-dist
Dynamic: requires-python
Dynamic: summary
